{
  "slug": "2015-infiniti-q50",
  "make": "Infiniti",
  "model": "Q50",
  "year": 2015,
  "source": "NHTSA complaints",
  "sourceUrl": "https://www.nhtsa.gov/vehicle/2015/INFINITI/Q50#complaints",
  "generatedAt": "2026-06-23T16:34:35.449Z",
  "total": 120,
  "issues": [
    {
      "component": "POWER TRAIN",
      "count": 37,
      "crash": 0,
      "fire": 1,
      "injuries": 0,
      "deaths": 0,
      "sample": "TL* THE CONTACT OWNS A 2015 INFINITI Q50. THE CONTACT STATED WHILE DRIVING APPROXIMATELY 70 MPH, THE VEHICLE JERKED, SHIFTED GEARS, REDUCED SPEED, THE ODOMETER FLASHED, THE CHECK ENGINE WARNING LIGHT ILLUMINATED, AND THE HEATING AND AIR CONDITIONING SYSTEM WENT FROM COLD TO HOT. ",
      "pct": 31
    },
    {
      "component": "STEERING",
      "count": 25,
      "crash": 3,
      "fire": 0,
      "injuries": 1,
      "deaths": 0,
      "sample": "THE VEHICLE SUDDENLY PULLS VERY HARD TO THE RIGHT REQUIRING FORCE TO KEEP IN A STRAIGHT LINE.  THE VEHICLE DID NOT EXPERIENCE ANY ALIGNMENT ALTERING POTHOLES OR ROAD BUMPS.  THIS IS A DANGEROUS SOFTWARE MALFUNCTION WITH THE DAS. I AM VERY LUCKY THIS OCCURRED AT LOW SPEED AND WITH",
      "pct": 21
    },
    {
      "component": "VEHICLE SPEED CONTROL",
      "count": 20,
      "crash": 0,
      "fire": 0,
      "injuries": 0,
      "deaths": 0,
      "sample": "CAME TO A SLOW STOP AT A RED LIGHT IN MY 2015 INFINITI Q50. MY FOOT WAS DIRECTLY ON THE BRAKE. WITHIN SECONDS THE CAR BEGAN TO PULL FORWARD AND I APPLIED ADDITIONAL PRESSURE ON THE BRAKES BY USING BOTH FEET. THE ENGINE WAS RACING OUT OF CONTROL AND THE TIRES WERE SCREECHING. SIFT",
      "pct": 17
    },
    {
      "component": "AIR BAGS",
      "count": 19,
      "crash": 9,
      "fire": 0,
      "injuries": 9,
      "deaths": 0,
      "sample": "HI, I PURCHASED THIS VEHICLE AT 7/31/2015. IT'S A BRAND NEW Q50 2015 PREMIUM. I MET TWO ISSUES ABOUT IT: 1. IT'S PASSENGER AIR BAG. THE PASSENGER AIR BAG STATUS LIGHT IS ON WITH AN ADULT OCCUPYING THE FRONT PASSENGER SEAT FOR THE FIRST A FEW MINUTES, SOMETIMES IS 2 MINS, SOMETIME",
      "pct": 16
    },
    {
      "component": "ELECTRICAL SYSTEM",
      "count": 17,
      "crash": 1,
      "fire": 1,
      "injuries": 1,
      "deaths": 0,
      "sample": "TL* THE CONTACT OWNS A 2015 INFINITI Q50. WHILE DRIVING APPROXIMATELY 40 MPH, THE VEHICLE LOST POWER AND CRASHED INTO A GUARDRAIL. THERE WERE NO WARNING INDICATORS ILLUMINATED BEFORE THE FAILURE. THE VEHICLE WAS TOWED TO AN INDEPENDENT MECHANIC. THE CONTACT SUSTAINED MINOR INJURI",
      "pct": 14
    }
  ],
  "narrative": {
    "headline": "What 2015 Infiniti Q50 owners report most",
    "summary": "Across 120 owner complaints to NHTSA, the most reported area is Power Train (31% of reports). Some reports involve a fire or crash — read the details below.",
    "issues": [
      {
        "component": "POWER TRAIN",
        "count": 37,
        "crash": 0,
        "fire": 1,
        "injuries": 0,
        "deaths": 0,
        "sample": "TL* THE CONTACT OWNS A 2015 INFINITI Q50. THE CONTACT STATED WHILE DRIVING APPROXIMATELY 70 MPH, THE VEHICLE JERKED, SHIFTED GEARS, REDUCED SPEED, THE ODOMETER FLASHED, THE CHECK ENGINE WARNING LIGHT ILLUMINATED, AND THE HEATING AND AIR CONDITIONING SYSTEM WENT FROM COLD TO HOT. ",
        "pct": 31,
        "title": "Power Train",
        "blurb": "37 reports (31%) · 1 fire"
      },
      {
        "component": "STEERING",
        "count": 25,
        "crash": 3,
        "fire": 0,
        "injuries": 1,
        "deaths": 0,
        "sample": "THE VEHICLE SUDDENLY PULLS VERY HARD TO THE RIGHT REQUIRING FORCE TO KEEP IN A STRAIGHT LINE.  THE VEHICLE DID NOT EXPERIENCE ANY ALIGNMENT ALTERING POTHOLES OR ROAD BUMPS.  THIS IS A DANGEROUS SOFTWARE MALFUNCTION WITH THE DAS. I AM VERY LUCKY THIS OCCURRED AT LOW SPEED AND WITH",
        "pct": 21,
        "title": "Steering",
        "blurb": "25 reports (21%) · 3 crash · 1 injured"
      },
      {
        "component": "VEHICLE SPEED CONTROL",
        "count": 20,
        "crash": 0,
        "fire": 0,
        "injuries": 0,
        "deaths": 0,
        "sample": "CAME TO A SLOW STOP AT A RED LIGHT IN MY 2015 INFINITI Q50. MY FOOT WAS DIRECTLY ON THE BRAKE. WITHIN SECONDS THE CAR BEGAN TO PULL FORWARD AND I APPLIED ADDITIONAL PRESSURE ON THE BRAKES BY USING BOTH FEET. THE ENGINE WAS RACING OUT OF CONTROL AND THE TIRES WERE SCREECHING. SIFT",
        "pct": 17,
        "title": "Vehicle Speed Control",
        "blurb": "20 reports (17%)"
      },
      {
        "component": "AIR BAGS",
        "count": 19,
        "crash": 9,
        "fire": 0,
        "injuries": 9,
        "deaths": 0,
        "sample": "HI, I PURCHASED THIS VEHICLE AT 7/31/2015. IT'S A BRAND NEW Q50 2015 PREMIUM. I MET TWO ISSUES ABOUT IT: 1. IT'S PASSENGER AIR BAG. THE PASSENGER AIR BAG STATUS LIGHT IS ON WITH AN ADULT OCCUPYING THE FRONT PASSENGER SEAT FOR THE FIRST A FEW MINUTES, SOMETIMES IS 2 MINS, SOMETIME",
        "pct": 16,
        "title": "Air Bags",
        "blurb": "19 reports (16%) · 9 crash · 9 injured"
      },
      {
        "component": "ELECTRICAL SYSTEM",
        "count": 17,
        "crash": 1,
        "fire": 1,
        "injuries": 1,
        "deaths": 0,
        "sample": "TL* THE CONTACT OWNS A 2015 INFINITI Q50. WHILE DRIVING APPROXIMATELY 40 MPH, THE VEHICLE LOST POWER AND CRASHED INTO A GUARDRAIL. THERE WERE NO WARNING INDICATORS ILLUMINATED BEFORE THE FAILURE. THE VEHICLE WAS TOWED TO AN INDEPENDENT MECHANIC. THE CONTACT SUSTAINED MINOR INJURI",
        "pct": 14,
        "title": "Electrical System",
        "blurb": "17 reports (14%) · 1 fire · 1 crash · 1 injured"
      }
    ]
  }
}