{
  "slug": "2016-dodge-dart",
  "make": "Dodge",
  "model": "Dart",
  "year": 2016,
  "source": "NHTSA complaints",
  "sourceUrl": "https://www.nhtsa.gov/vehicle/2016/DODGE/DART#complaints",
  "generatedAt": "2026-06-23T16:29:26.524Z",
  "total": 243,
  "issues": [
    {
      "component": "POWER TRAIN",
      "count": 72,
      "crash": 2,
      "fire": 0,
      "injuries": 0,
      "deaths": 0,
      "sample": "TL* THE CONTACT OWNS A 2016 DODGE DART. WHILE DRIVING VARIOUS SPEEDS OR WHILE IN STOP AND GO TRAFFIC, THE VEHICLE SUDDENLY JERKED. THE CONTACT STATED THAT THE VEHICLE WAS EQUIPPED WITH AN AUTO STICK OPTION, WHICH MEANT THE VEHICLE COULD BE DRIVEN IN AUTOMATIC OR MANUAL MODE. WHEN",
      "pct": 30
    },
    {
      "component": "ENGINE",
      "count": 66,
      "crash": 0,
      "fire": 3,
      "injuries": 0,
      "deaths": 0,
      "sample": "ON A CITY STREET, TRIED TO ACCELERATE AT A STOP LIGHT WITH THE BRAKE ON. WOULD NOT ACCELERATE TURNING LEFT IN ONCOMING TRAFFIC.INTERMITTENLY (HOPS) IN MOTION EXITING A HIGHWAY, UPON BRAKING I TRAFFIC, STOPPED AT A TRAFFIC LIGHT AND IN THE DRIVEWAY WITH THE KEY REMOVED. TACHOMETER",
      "pct": 27
    },
    {
      "component": "ELECTRICAL SYSTEM",
      "count": 47,
      "crash": 1,
      "fire": 1,
      "injuries": 3,
      "deaths": 0,
      "sample": "ON A CITY STREET, TRIED TO ACCELERATE AT A STOP LIGHT WITH THE BRAKE ON. WOULD NOT ACCELERATE TURNING LEFT IN ONCOMING TRAFFIC.INTERMITTENLY (HOPS) IN MOTION EXITING A HIGHWAY, UPON BRAKING I TRAFFIC, STOPPED AT A TRAFFIC LIGHT AND IN THE DRIVEWAY WITH THE KEY REMOVED. TACHOMETER",
      "pct": 19
    },
    {
      "component": "SERVICE BRAKES",
      "count": 26,
      "crash": 4,
      "fire": 0,
      "injuries": 4,
      "deaths": 0,
      "sample": "WHILE DRIVING THIS CAR AT MULTIPLE SPEEDS, THE CAR SLOWS DOWN AND COMES TO A COMPLETE STOP, I HEAR A NOISE AND THE GAS PEDAL VIBRATES, THE STEERING AND GAS PEDAL LOCKS UP. THIS EVENT HAS HAPPENED 3 TIMES WITHIN FOUR DAYS LEAVING FROM MY GARAGE, ON THE INTERSTATE AND A CITY STREET",
      "pct": 11
    },
    {
      "component": "FUEL/PROPULSION SYSTEM",
      "count": 13,
      "crash": 0,
      "fire": 2,
      "injuries": 0,
      "deaths": 0,
      "sample": "THE PREVIOUS COMPLAINT WAS FILED ON SEPTEMBER 15, 2016. IHTSA ID NUMBER 10906998.    ORIGINALLY THE VEHICLE DYING WAS SAID TO BE DUE TO THE OIL NEEDING TO BE CHANGED AND SOMETHING WITH THE TURBO ENGINE THAT MY VEHICLE DOES NOT HAVE. SINCE THE PREVIOUS COMPLAINT, THE COMPUTER SYST",
      "pct": 5
    }
  ],
  "narrative": {
    "headline": "What 2016 Dodge Dart owners report most",
    "summary": "Across 243 owner complaints to NHTSA, the most reported area is Power Train (30% of reports). Some reports involve a fire or crash — read the details below.",
    "issues": [
      {
        "component": "POWER TRAIN",
        "count": 72,
        "crash": 2,
        "fire": 0,
        "injuries": 0,
        "deaths": 0,
        "sample": "TL* THE CONTACT OWNS A 2016 DODGE DART. WHILE DRIVING VARIOUS SPEEDS OR WHILE IN STOP AND GO TRAFFIC, THE VEHICLE SUDDENLY JERKED. THE CONTACT STATED THAT THE VEHICLE WAS EQUIPPED WITH AN AUTO STICK OPTION, WHICH MEANT THE VEHICLE COULD BE DRIVEN IN AUTOMATIC OR MANUAL MODE. WHEN",
        "pct": 30,
        "title": "Power Train",
        "blurb": "72 reports (30%) · 2 crash"
      },
      {
        "component": "ENGINE",
        "count": 66,
        "crash": 0,
        "fire": 3,
        "injuries": 0,
        "deaths": 0,
        "sample": "ON A CITY STREET, TRIED TO ACCELERATE AT A STOP LIGHT WITH THE BRAKE ON. WOULD NOT ACCELERATE TURNING LEFT IN ONCOMING TRAFFIC.INTERMITTENLY (HOPS) IN MOTION EXITING A HIGHWAY, UPON BRAKING I TRAFFIC, STOPPED AT A TRAFFIC LIGHT AND IN THE DRIVEWAY WITH THE KEY REMOVED. TACHOMETER",
        "pct": 27,
        "title": "Engine",
        "blurb": "66 reports (27%) · 3 fire"
      },
      {
        "component": "ELECTRICAL SYSTEM",
        "count": 47,
        "crash": 1,
        "fire": 1,
        "injuries": 3,
        "deaths": 0,
        "sample": "ON A CITY STREET, TRIED TO ACCELERATE AT A STOP LIGHT WITH THE BRAKE ON. WOULD NOT ACCELERATE TURNING LEFT IN ONCOMING TRAFFIC.INTERMITTENLY (HOPS) IN MOTION EXITING A HIGHWAY, UPON BRAKING I TRAFFIC, STOPPED AT A TRAFFIC LIGHT AND IN THE DRIVEWAY WITH THE KEY REMOVED. TACHOMETER",
        "pct": 19,
        "title": "Electrical System",
        "blurb": "47 reports (19%) · 1 fire · 1 crash · 3 injured"
      },
      {
        "component": "SERVICE BRAKES",
        "count": 26,
        "crash": 4,
        "fire": 0,
        "injuries": 4,
        "deaths": 0,
        "sample": "WHILE DRIVING THIS CAR AT MULTIPLE SPEEDS, THE CAR SLOWS DOWN AND COMES TO A COMPLETE STOP, I HEAR A NOISE AND THE GAS PEDAL VIBRATES, THE STEERING AND GAS PEDAL LOCKS UP. THIS EVENT HAS HAPPENED 3 TIMES WITHIN FOUR DAYS LEAVING FROM MY GARAGE, ON THE INTERSTATE AND A CITY STREET",
        "pct": 11,
        "title": "Service Brakes",
        "blurb": "26 reports (11%) · 4 crash · 4 injured"
      },
      {
        "component": "FUEL/PROPULSION SYSTEM",
        "count": 13,
        "crash": 0,
        "fire": 2,
        "injuries": 0,
        "deaths": 0,
        "sample": "THE PREVIOUS COMPLAINT WAS FILED ON SEPTEMBER 15, 2016. IHTSA ID NUMBER 10906998.    ORIGINALLY THE VEHICLE DYING WAS SAID TO BE DUE TO THE OIL NEEDING TO BE CHANGED AND SOMETHING WITH THE TURBO ENGINE THAT MY VEHICLE DOES NOT HAVE. SINCE THE PREVIOUS COMPLAINT, THE COMPUTER SYST",
        "pct": 5,
        "title": "Fuel/Propulsion System",
        "blurb": "13 reports (5%) · 2 fire"
      }
    ]
  }
}