{
  "slug": "2018-buick-encore",
  "make": "Buick",
  "model": "Encore",
  "year": 2018,
  "source": "NHTSA complaints",
  "sourceUrl": "https://www.nhtsa.gov/vehicle/2018/BUICK/ENCORE#complaints",
  "generatedAt": "2026-06-23T16:27:21.872Z",
  "total": 71,
  "issues": [
    {
      "component": "ENGINE",
      "count": 27,
      "crash": 0,
      "fire": 0,
      "injuries": 0,
      "deaths": 0,
      "sample": "THERE IS A MALFUNCTION WITH THE TURBO HOSE ON A MAJORITY OF 2018 BUICK ENCORE'S THAT REQUIRE A NEW HOSE. THERE IS A NATIONWIDE BACK ORDER ON THESE PARTS DUE TO ALL OF THE REPAIRS. WHEN THIS ITEM BROKE I WAS DRIVING ABOUT 70 MPH ON THE INTERSTATE, THERE WAS A LOUD POP FROM THE ENG",
      "pct": 38
    },
    {
      "component": "SERVICE BRAKES",
      "count": 11,
      "crash": 4,
      "fire": 0,
      "injuries": 1,
      "deaths": 0,
      "sample": "I HAVE COMPLIN TO MY DEALER ABOUT MY CAR EXCELERATING WHEN I HIT THE BRAKES . THEY SAID THEY CAN FIND A PROBLEM , WELL IT HAPPEN AGAIN ON AUGUST 29 2019 AN IT CAUSE A ACCIDENT I WAS DRIVING ON A 6 LANE ROADWAY AROUND 330 IN THE AFTERNOON  I WAS IN CRUISE CONTROL AT 45 MPH AN WHEN",
      "pct": 15
    },
    {
      "component": "POWER TRAIN",
      "count": 10,
      "crash": 1,
      "fire": 0,
      "injuries": 0,
      "deaths": 0,
      "sample": "TL* THE CONTACT OWNS A 2018 BUICK ENCORE. WHILE THE VEHICLE WAS PARKED AND UNOCCUPIED, IT INADVERTENTLY ROLLED AWAY AND CRASHED INTO ANOTHER VEHICLE. A POLICE REPORT WAS FILED. THERE WERE NO INJURIES. THE VEHICLE WAS TAKEN TO A DEALER (NYE BUICK GMC, 1421 GENESEE ST, ONEIDA, NY 1",
      "pct": 14
    },
    {
      "component": "AIR BAGS",
      "count": 10,
      "crash": 6,
      "fire": 0,
      "injuries": 8,
      "deaths": 0,
      "sample": "AIRBAGS DID NOT DEPLOY UPON AUTO ACCIDENT. IMPACT AREA WAS FRONT CORNER FENDER ON PASSENGER SIDE. POSSIBLE GAS RELEASED INTO PASSENGER SIDE OF CABIN SMELLED 'ELECTRICAL' AND 'SMOKE' FILLED PASSENGER FOOTBOARD AREA. NO LOSS OF COOLANT FROM CAR TO EXPLAIN SMOKE. AIRBAG WARNING LIGH",
      "pct": 14
    },
    {
      "component": "ELECTRICAL SYSTEM",
      "count": 9,
      "crash": 0,
      "fire": 0,
      "injuries": 0,
      "deaths": 0,
      "sample": "SINCE I BOUGHT THIS CAR IN 04/2018 I HAD MANY PROBLEMS PROBLEMS AS THE  ENGINE SENSOR HAD TO BE REPLACED, HEADLIGHTS GOING OUT WHEN I WAS DRIVING, THEY COULD NOT REPRODUCE THE PROBLEM AT THE DEALERSHIP , NOW THE BACK WHEEL DRIVER MODULE IS BAD,IT WILL NEED TO BE REPLACED ,AND FIN",
      "pct": 13
    }
  ],
  "narrative": {
    "headline": "What 2018 Buick Encore owners report most",
    "summary": "Across 71 owner complaints to NHTSA, the most reported area is Engine (38% of reports). Some reports involve a fire or crash — read the details below.",
    "issues": [
      {
        "component": "ENGINE",
        "count": 27,
        "crash": 0,
        "fire": 0,
        "injuries": 0,
        "deaths": 0,
        "sample": "THERE IS A MALFUNCTION WITH THE TURBO HOSE ON A MAJORITY OF 2018 BUICK ENCORE'S THAT REQUIRE A NEW HOSE. THERE IS A NATIONWIDE BACK ORDER ON THESE PARTS DUE TO ALL OF THE REPAIRS. WHEN THIS ITEM BROKE I WAS DRIVING ABOUT 70 MPH ON THE INTERSTATE, THERE WAS A LOUD POP FROM THE ENG",
        "pct": 38,
        "title": "Engine",
        "blurb": "27 reports (38%)"
      },
      {
        "component": "SERVICE BRAKES",
        "count": 11,
        "crash": 4,
        "fire": 0,
        "injuries": 1,
        "deaths": 0,
        "sample": "I HAVE COMPLIN TO MY DEALER ABOUT MY CAR EXCELERATING WHEN I HIT THE BRAKES . THEY SAID THEY CAN FIND A PROBLEM , WELL IT HAPPEN AGAIN ON AUGUST 29 2019 AN IT CAUSE A ACCIDENT I WAS DRIVING ON A 6 LANE ROADWAY AROUND 330 IN THE AFTERNOON  I WAS IN CRUISE CONTROL AT 45 MPH AN WHEN",
        "pct": 15,
        "title": "Service Brakes",
        "blurb": "11 reports (15%) · 4 crash · 1 injured"
      },
      {
        "component": "POWER TRAIN",
        "count": 10,
        "crash": 1,
        "fire": 0,
        "injuries": 0,
        "deaths": 0,
        "sample": "TL* THE CONTACT OWNS A 2018 BUICK ENCORE. WHILE THE VEHICLE WAS PARKED AND UNOCCUPIED, IT INADVERTENTLY ROLLED AWAY AND CRASHED INTO ANOTHER VEHICLE. A POLICE REPORT WAS FILED. THERE WERE NO INJURIES. THE VEHICLE WAS TAKEN TO A DEALER (NYE BUICK GMC, 1421 GENESEE ST, ONEIDA, NY 1",
        "pct": 14,
        "title": "Power Train",
        "blurb": "10 reports (14%) · 1 crash"
      },
      {
        "component": "AIR BAGS",
        "count": 10,
        "crash": 6,
        "fire": 0,
        "injuries": 8,
        "deaths": 0,
        "sample": "AIRBAGS DID NOT DEPLOY UPON AUTO ACCIDENT. IMPACT AREA WAS FRONT CORNER FENDER ON PASSENGER SIDE. POSSIBLE GAS RELEASED INTO PASSENGER SIDE OF CABIN SMELLED 'ELECTRICAL' AND 'SMOKE' FILLED PASSENGER FOOTBOARD AREA. NO LOSS OF COOLANT FROM CAR TO EXPLAIN SMOKE. AIRBAG WARNING LIGH",
        "pct": 14,
        "title": "Air Bags",
        "blurb": "10 reports (14%) · 6 crash · 8 injured"
      },
      {
        "component": "ELECTRICAL SYSTEM",
        "count": 9,
        "crash": 0,
        "fire": 0,
        "injuries": 0,
        "deaths": 0,
        "sample": "SINCE I BOUGHT THIS CAR IN 04/2018 I HAD MANY PROBLEMS PROBLEMS AS THE  ENGINE SENSOR HAD TO BE REPLACED, HEADLIGHTS GOING OUT WHEN I WAS DRIVING, THEY COULD NOT REPRODUCE THE PROBLEM AT THE DEALERSHIP , NOW THE BACK WHEEL DRIVER MODULE IS BAD,IT WILL NEED TO BE REPLACED ,AND FIN",
        "pct": 13,
        "title": "Electrical System",
        "blurb": "9 reports (13%)"
      }
    ]
  }
}