{
  "slug": "2020-audi-s3",
  "make": "Audi",
  "model": "S3",
  "year": 2020,
  "source": "NHTSA complaints",
  "sourceUrl": "https://www.nhtsa.gov/vehicle/2020/AUDI/S3#complaints",
  "generatedAt": "2026-06-23T16:43:03.168Z",
  "total": 1,
  "issues": [
    {
      "component": "UNKNOWN OR OTHER",
      "count": 1,
      "crash": 0,
      "fire": 0,
      "injuries": 0,
      "deaths": 0,
      "sample": "1) Sunroof exploded while merging onto highway from a rest stop (I believe I was still on the on ramp at the time) - Vehicle in the process of being fixed so probably not available for inspection but the collision shop has pictures 2) Fortunate I didn't freak out and was able to ",
      "pct": 100
    }
  ],
  "narrative": {
    "headline": "What 2020 Audi S3 owners report most",
    "summary": "Across 1 owner complaints to NHTSA, the most reported area is Unknown Or Other (100% of reports).",
    "issues": [
      {
        "component": "UNKNOWN OR OTHER",
        "count": 1,
        "crash": 0,
        "fire": 0,
        "injuries": 0,
        "deaths": 0,
        "sample": "1) Sunroof exploded while merging onto highway from a rest stop (I believe I was still on the on ramp at the time) - Vehicle in the process of being fixed so probably not available for inspection but the collision shop has pictures 2) Fortunate I didn't freak out and was able to ",
        "pct": 100,
        "title": "Unknown Or Other",
        "blurb": "1 report (100%)"
      }
    ]
  }
}